src/uart_rx.v
module uart_rx#(
  parameter CLKS_PER_BIT = 5208
)(
  input        i_Clock,
  input        i_Rx_Serial,
  output       o_Rx_DV,
  output [7:0] o_Rx_Byte
);
  parameter s_IDLE         = 3'b000;
  parameter s_RX_START_BIT = 3'b001;
  parameter s_RX_DATA_BITS = 3'b010;
  parameter s_RX_STOP_BIT  = 3'b011;
  parameter s_CLEANUP      = 3'b100;

  reg           r_Rx_Data_R = 1'b1;
  reg           r_Rx_Data   = 1'b1;

  reg [7:0]     r_Clock_Count = 0;
  reg [2:0]     r_Bit_Index   = 0;
  reg [7:0]     r_Rx_Byte     = 0;
  reg           r_Rx_DV       = 0;
  reg [2:0]     r_SM_Main     = 0;
  always @(posedge i_Clock) begin
    r_Rx_Data_R <= i_Rx_Serial;
    r_Rx_Data <= r_Rx_Data_R;
  end
  always @(posedge i_Clock) begin
    case (r_SM_Main)
      s_IDLE : begin
        r_Rx_DV <= 1'b0;
        r_Clock_Count <= 0;
        r_Bit_Index <= 0;
        if(r_Rx_Data == 1'b0)
          r_SM_Main <= s_RX_START_BIT;
        else
          r_SM_Main <= s_IDLE;
      end
      s_RX_START_BIT : begin
        if(r_Clock_Count == (CLKS_PER_BIT-1)/2) begin
          if(r_Rx_Data == 1'b0) begin
            r_Clock_Count <= 0;
            r_SM_Main <= s_RX_DATA_BITS;
          end
          else
            r_SM_Main <= s_IDLE;
        end
        else begin
          r_Clock_Count <= r_Clock_Count + 1;
          r_SM_Main <= s_RX_START_BIT;
        end
      end
      s_RX_DATA_BITS : begin
        if(r_Clock_Count < CLKS_PER_BIT-1) begin
          r_Clock_Count <= r_Clock_Count + 1;
          r_SM_Main <= s_RX_DATA_BITS;
        end
        else begin
          r_Clock_Count <= 0;
          r_Rx_Byte[r_Bit_Index] <= r_Rx_Data;
          if(r_Bit_Index < 7) begin
            r_Bit_Index <= r_Bit_Index + 1;
            r_SM_Main <= s_RX_DATA_BITS;
          end
          else begin
            r_Bit_Index <= 0;
            r_SM_Main <= s_RX_STOP_BIT;
          end
        end
      end
      s_RX_STOP_BIT : begin
        if(r_Clock_Count < CLKS_PER_BIT-1) begin
          r_Clock_Count <= r_Clock_Count + 1;
          r_SM_Main <= s_RX_STOP_BIT;
        end
        else begin
          r_Rx_DV <= 1'b1;
          r_Clock_Count <= 0;
          r_SM_Main <= s_CLEANUP;
        end
      end
      s_CLEANUP : begin
        r_SM_Main <= s_IDLE;
        r_Rx_DV <= 1'b0;
      end
      default : r_SM_Main <= s_IDLE;
    endcase
  end
  assign o_Rx_DV = r_Rx_DV;
  assign o_Rx_Byte = r_Rx_Byte;
endmodule

src/uart_tx.v
module uart_tx#(
  parameter CLKS_PER_BIT = 5208
)(
  input       i_Clock,
  input       i_Tx_DV,
  input [7:0] i_Tx_Byte,
  output      o_Tx_Active,
  output reg  o_Tx_Serial,
  output      o_Tx_Done
);
  parameter s_IDLE         = 3'b000;
  parameter s_TX_START_BIT = 3'b001;
  parameter s_TX_DATA_BITS = 3'b010;
  parameter s_TX_STOP_BIT  = 3'b011;
  parameter s_CLEANUP      = 3'b100;

  reg [2:0]    r_SM_Main     = 0;
  reg [7:0]    r_Clock_Count = 0;
  reg [2:0]    r_Bit_Index   = 0;
  reg [7:0]    r_Tx_Data     = 0;
  reg          r_Tx_Done     = 0;
  reg          r_Tx_Active   = 0;

  always @(posedge i_Clock) begin
    case(r_SM_Main)
      s_IDLE :
        begin
          o_Tx_Serial <= 1'b1;
          r_Tx_Done <= 1'b0;
          r_Clock_Count <= 0;
          r_Bit_Index <= 0;
          if(i_Tx_DV == 1'b1)
            begin
              r_Tx_Active <= 1'b1;
              r_Tx_Data <= i_Tx_Byte;
              r_SM_Main <= s_TX_START_BIT;
            end
          else
            r_SM_Main <= s_IDLE;
        end
      s_TX_START_BIT : begin
        o_Tx_Serial <= 1'b0;
        if(r_Clock_Count < CLKS_PER_BIT-1) begin
          r_Clock_Count <= r_Clock_Count + 1;
          r_SM_Main <= s_TX_START_BIT;
        end
        else begin
          r_Clock_Count <= 0;
          r_SM_Main <= s_TX_DATA_BITS;
        end
      end
      s_TX_DATA_BITS : begin
        o_Tx_Serial <= r_Tx_Data[r_Bit_Index];
        if(r_Clock_Count < CLKS_PER_BIT-1) begin
          r_Clock_Count <= r_Clock_Count + 1;
          r_SM_Main <= s_TX_DATA_BITS;
        end
        else begin
          r_Clock_Count <= 0;
          if(r_Bit_Index < 7) begin
            r_Bit_Index <= r_Bit_Index + 1;
            r_SM_Main <= s_TX_DATA_BITS;
          end
          else begin
            r_Bit_Index <= 0;
            r_SM_Main <= s_TX_STOP_BIT;
          end
        end
      end
      s_TX_STOP_BIT : begin
        o_Tx_Serial <= 1'b1;
        if(r_Clock_Count < CLKS_PER_BIT-1) begin
          r_Clock_Count <= r_Clock_Count + 1;
          r_SM_Main <= s_TX_STOP_BIT;
        end
        else begin
          r_Tx_Done <= 1'b1;
          r_Clock_Count <= 0;
          r_SM_Main <= s_CLEANUP;
          r_Tx_Active <= 1'b0;
        end
      end
      s_CLEANUP : begin
        r_Tx_Done <= 1'b1;
        r_SM_Main <= s_IDLE;
      end
      default : r_SM_Main <= s_IDLE;
    endcase
  end
  assign o_Tx_Active = r_Tx_Active;
  assign o_Tx_Done = r_Tx_Done;
endmodule

src/uart_top.v
module uart_top#(
  parameter CLK_HZ = 50_000_000,
  parameter BIT_RATE = 9600,
  parameter PAYLOAD_BITS = 8,
  parameter STOP_BITS = 1
)(
  input  wire clk,
  input  wire rst_n,
  input  wire uart_rx_in,
  input  wire tx_start,
  input  wire [PAYLOAD_BITS-1:0] tx_data,
  output wire uart_tx_out,
  output wire tx_busy,
  output wire [PAYLOAD_BITS-1:0] rx_data,
  output wire rx_valid
);
  localparam CLKS_PER_BIT = CLK_HZ / BIT_RATE;
  wire tx_done;

  uart_tx#(
    .CLKS_PER_BIT(CLKS_PER_BIT)
  )uart_tx_inst(
    .i_Clock(clk),
    .i_Tx_DV(tx_start),
    .i_Tx_Byte(tx_data),
    .o_Tx_Active(tx_busy),
    .o_Tx_Serial(uart_tx_out),
    .o_Tx_Done(tx_done)
  );

  uart_rx#(
    .CLKS_PER_BIT(CLKS_PER_BIT)
  )uart_rx_inst(
    .i_Clock(clk),
    .i_Rx_Serial(uart_rx_in),
    .o_Rx_DV(rx_valid),
    .o_Rx_Byte(rx_data)
  );
endmodule

src/uart_tb.v
`timescale 1ns/1ps

module uart_top_tb;
  localparam CLK_HZ       = 50_000_000;
  localparam BIT_RATE     = 1_000_000;
  localparam PAYLOAD_BITS = 8;
  localparam STOP_BITS    = 1;
  localparam CLK_PERIOD   = 20;

  reg clk;
  reg rst_n;
  reg tx_start;
  reg [PAYLOAD_BITS-1:0] tx_data;
  wire uart_tx_out;
  wire tx_busy;
  wire [PAYLOAD_BITS-1:0] rx_data;
  wire rx_valid;
  wire uart_rx_in;

  assign uart_rx_in = uart_tx_out;

  uart_top#(
    .CLK_HZ(CLK_HZ),
    .BIT_RATE(BIT_RATE),
    .PAYLOAD_BITS(PAYLOAD_BITS),
    .STOP_BITS(STOP_BITS)
  ) dut (
    .clk(clk),
    .rst_n(rst_n),
    .uart_rx_in(uart_rx_in),
    .tx_start(tx_start),
    .tx_data(tx_data),
    .uart_tx_out(uart_tx_out),
    .tx_busy(tx_busy),
    .rx_data(rx_data),
    .rx_valid(rx_valid)
  );

  always #(CLK_PERIOD/2) clk = ~clk;

  initial begin
    $dumpfile("uart_top_tb.vcd");
    $dumpvars(0, uart_top_tb);

    clk = 0;
    rst_n = 0;
    tx_start = 0;
    tx_data = 0;

    #(10*CLK_PERIOD);
    rst_n = 1;
    $display("[%0t] Reset deasserted", $time);

    #(10*CLK_PERIOD);
    tx_data = 8'hA5;
    tx_start = 1;
    $display("[%0t] TX Start: Sending 0x%0h", $time, tx_data);
    #(CLK_PERIOD);
    tx_start = 0;

    wait (rx_valid);
    $display("[%0t] RX Received: 0x%0h", $time, rx_data);

    if (rx_data == tx_data)
      $display("[%0t] TEST PASSED ✅", $time);
    else
      $display("[%0t] TEST FAILED ❌ (Expected: 0x%0h, Got: 0x%0h)", $time, tx_data, rx_data);

    #(10*CLK_PERIOD);
    $finish;
  end
endmodule

src/uart_top_tb.vcd
$date
	Sat Nov  8 11:43:52 2025
$end
$version
	Icarus Verilog
$end
$timescale
	1ps
$end
$scope module uart_top_tb $end
$var wire 1 ! uart_rx_in $end
$var wire 1 " uart_tx_out $end
$var wire 1 # tx_busy $end
$var wire 1 $ rx_valid $end
$var wire 8 % rx_data [7:0] $end
$var reg 1 & clk $end
$var reg 1 ' rst_n $end
$var reg 8 ( tx_data [7:0] $end
$var reg 1 ) tx_start $end
$scope module dut $end
$var wire 1 & clk $end
$var wire 1 ' rst_n $end
$var wire 8 * tx_data [7:0] $end
$var wire 1 ) tx_start $end
$var wire 1 ! uart_rx_in $end
$var wire 1 " uart_tx_out $end
$var wire 1 + tx_done $end
$var wire 1 # tx_busy $end
$var wire 1 $ rx_valid $end
$var wire 8 , rx_data [7:0] $end
$scope module uart_rx_inst $end
$var wire 1 & i_Clock $end
$var wire 1 ! i_Rx_Serial $end
$var wire 8 - o_Rx_Byte [7:0] $end
$var wire 1 $ o_Rx_DV $end
$var reg 3 . r_Bit_Index [2:0] $end
$var reg 8 / r_Clock_Count [7:0] $end
$var reg 8 0 r_Rx_Byte [7:0] $end
$var reg 1 1 r_Rx_DV $end
$var reg 1 2 r_Rx_Data $end
$var reg 1 3 r_Rx_Data_R $end
$var reg 3 4 r_SM_Main [2:0] $end
$upscope $end
$scope module uart_tx_inst $end
$var wire 1 & i_Clock $end
$var wire 8 5 i_Tx_Byte [7:0] $end
$var wire 1 ) i_Tx_DV $end
$var wire 1 # o_Tx_Active $end
$var wire 1 + o_Tx_Done $end
$var reg 1 " o_Tx_Serial $end
$var reg 3 6 r_Bit_Index [2:0] $end
$var reg 8 7 r_Clock_Count [7:0] $end
$var reg 3 8 r_SM_Main [2:0] $end
$var reg 1 9 r_Tx_Active $end
$var reg 8 : r_Tx_Data [7:0] $end
$var reg 1 ; r_Tx_Done $end
$upscope $end
$upscope $end
$upscope $end
$enddefinitions $end
#0
$dumpvars
0;
b0 :
09
b0 8
b0 7
b0 6
b0 5
b0 4
13
12
01
b0 0
b0 /
b0 .
b0 -
b0 ,
0+
b0 *
0)
b0 (
0'
0&
b0 %
0$
0#
x"
x!
$end
#10000
1!
1"
x3
1&
#20000
0&
#30000
x2
13
1&
#40000
0&
#50000
12
1&
#60000
0&
#70000
1&
#80000
0&
#90000
1&
#100000
0&
#110000
1&
#120000
0&
#130000
1&
#140000
0&
#150000
1&
#160000
0&
#170000
1&
#180000
0&
#190000
1&
#200000
0&
1'
#210000
1&
#220000
0&
#230000
1&
#240000
0&
#250000
1&
#260000
0&
#270000
1&
#280000
0&
#290000
1&
#300000
0&
#310000
1&
#320000
0&
#330000
1&
#340000
0&
#350000
1&
#360000
0&
#370000
1&
#380000
0&
#390000
1&
#400000
0&
1)
b10100101 (
b10100101 *
b10100101 5
#410000
b1 8
b10100101 :
1#
19
1&
#420000
0&
0)
#430000
b1 7
0!
0"
1&
#440000
0&
#450000
b10 7
03
1&
#460000
0&
#470000
02
b11 7
1&
#480000
0&
#490000
b100 7
b1 4
1&
#500000
0&
#510000
b1 /
b101 7
1&
#520000
0&
#530000
b110 7
b10 /
1&
#540000
0&
#550000
b11 /
b111 7
1&
#560000
0&
#570000
b1000 7
b100 /
1&
#580000
0&
#590000
b101 /
b1001 7
1&
#600000
0&
#610000
b1010 7
b110 /
1&
#620000
0&
#630000
b111 /
b1011 7
1&
#640000
0&
#650000
b1100 7
b1000 /
1&
#660000
0&
#670000
b1001 /
b1101 7
1&
#680000
0&
#690000
b1110 7
b1010 /
1&
#700000
0&
#710000
b1011 /
b1111 7
1&
#720000
0&
#730000
b10000 7
b1100 /
1&
#740000
0&
#750000
b1101 /
b10001 7
1&
#760000
0&
#770000
b10010 7
b1110 /
1&
#780000
0&
#790000
b1111 /
b10011 7
1&
#800000
0&
#810000
b10100 7
b10000 /
1&
#820000
0&
#830000
b10001 /
b10101 7
1&
#840000
0&
#850000
b10110 7
b10010 /
1&
#860000
0&
#870000
b10011 /
b10111 7
1&
#880000
0&
#890000
b11000 7
b10100 /
1&
#900000
0&
#910000
b10101 /
b11001 7
1&
#920000
0&
#930000
b11010 7
b10110 /
1&
#940000
0&
#950000
b10111 /
b11011 7
1&
#960000
0&
#970000
b11100 7
b11000 /
1&
#980000
0&
#990000
b10 4
b0 /
b11101 7
1&
#1000000
0&
#1010000
b11110 7
b1 /
1&
#1020000
0&
#1030000
b10 /
b11111 7
1&
#1040000
0&
#1050000
b100000 7
b11 /
1&
#1060000
0&
#1070000
b100 /
b100001 7
1&
#1080000
0&
#1090000
b100010 7
b101 /
1&
#1100000
0&
#1110000
b110 /
b100011 7
1&
#1120000
0&
#1130000
b100100 7
b111 /
1&
#1140000
0&
#1150000
b1000 /
b100101 7
1&
#1160000
0&
#1170000
b100110 7
b1001 /
1&
#1180000
0&
#1190000
b1010 /
b100111 7
1&
#1200000
0&
#1210000
b101000 7
b1011 /
1&
#1220000
0&
#1230000
b1100 /
b101001 7
1&
#1240000
0&
#1250000
b101010 7
b1101 /
1&
#1260000
0&
#1270000
b1110 /
b101011 7
1&
#1280000
0&
#1290000
b101100 7
b1111 /
1&
#1300000
0&
#1310000
b10000 /
b101101 7
1&
#1320000
0&
#1330000
b101110 7
b10001 /
1&
#1340000
0&
#1350000
b10010 /
b101111 7
1&
#1360000
0&
#1370000
b110000 7
b10011 /
1&
#1380000
0&
#1390000
b10100 /
b110001 7
1&
#1400000
0&
#1410000
b10 8
b0 7
b10101 /
1&
#1420000
0&
#1430000
b10110 /
b1 7
1!
1"
1&
#1440000
0&
#1450000
b10 7
13
b10111 /
1&
#1460000
0&
#1470000
b11000 /
12
b11 7
1&
#1480000
0&
#1490000
b100 7
b11001 /
1&
#1500000
0&
#1510000
b11010 /
b101 7
1&
#1520000
0&
#1530000
b110 7
b11011 /
1&
#1540000
0&
#1550000
b11100 /
b111 7
1&
#1560000
0&
#1570000
b1000 7
b11101 /
1&
#1580000
0&
#1590000
b11110 /
b1001 7
1&
#1600000
0&
#1610000
b1010 7
b11111 /
1&
#1620000
0&
#1630000
b100000 /
b1011 7
1&
#1640000
0&
#1650000
b1100 7
b100001 /
1&
#1660000
0&
#1670000
b100010 /
b1101 7
1&
#1680000
0&
#1690000
b1110 7
b100011 /
1&
#1700000
0&
#1710000
b100100 /
b1111 7
1&
#1720000
0&
#1730000
b10000 7
b100101 /
1&
#1740000
0&
#1750000
b100110 /
b10001 7
1&
#1760000
0&
#1770000
b10010 7
b100111 /
1&
#1780000
0&
#1790000
b101000 /
b10011 7
1&
#1800000
0&
#1810000
b10100 7
b101001 /
1&
#1820000
0&
#1830000
b101010 /
b10101 7
1&
#1840000
0&
#1850000
b10110 7
b101011 /
1&
#1860000
0&
#1870000
b101100 /
b10111 7
1&
#1880000
0&
#1890000
b11000 7
b101101 /
1&
#1900000
0&
#1910000
b101110 /
b11001 7
1&
#1920000
0&
#1930000
b11010 7
b101111 /
1&
#1940000
0&
#1950000
b110000 /
b11011 7
1&
#1960000
0&
#1970000
b11100 7
b110001 /
1&
#1980000
0&
#1990000
b1 .
b1 %
b1 ,
b1 -
b1 0
b0 /
b11101 7
1&
#2000000
0&
#2010000
b11110 7
b1 /
1&
#2020000
0&
#2030000
b10 /
b11111 7
1&
#2040000
0&
#2050000
b100000 7
b11 /
1&
#2060000
0&
#2070000
b100 /
b100001 7
1&
#2080000
0&
#2090000
b100010 7
b101 /
1&
#2100000
0&
#2110000
b110 /
b100011 7
1&
#2120000
0&
#2130000
b100100 7
b111 /
1&
#2140000
0&
#2150000
b1000 /
b100101 7
1&
#2160000
0&
#2170000
b100110 7
b1001 /
1&
#2180000
0&
#2190000
b1010 /
b100111 7
1&
#2200000
0&
#2210000
b101000 7
b1011 /
1&
#2220000
0&
#2230000
b1100 /
b101001 7
1&
#2240000
0&
#2250000
b101010 7
b1101 /
1&
#2260000
0&
#2270000
b1110 /
b101011 7
1&
#2280000
0&
#2290000
b101100 7
b1111 /
1&
#2300000
0&
#2310000
b10000 /
b101101 7
1&
#2320000
0&
#2330000
b101110 7
b10001 /
1&
#2340000
0&
#2350000
b10010 /
b101111 7
1&
#2360000
0&
#2370000
b110000 7
b10011 /
1&
#2380000
0&
#2390000
b10100 /
b110001 7
1&
#2400000
0&
#2410000
b1 6
b0 7
b10101 /
1&
#2420000
0&
#2430000
b10110 /
b1 7
0!
0"
1&
#2440000
0&
#2450000
b10 7
03
b10111 /
1&
#2460000
0&
#2470000
b11000 /
02
b11 7
1&
#2480000
0&
#2490000
b100 7
b11001 /
1&
#2500000
0&
#2510000
b11010 /
b101 7
1&
#2520000
0&
#2530000
b110 7
b11011 /
1&
#2540000
0&
#2550000
b11100 /
b111 7
1&
#2560000
0&
#2570000
b1000 7
b11101 /
1&
#2580000
0&
#2590000
b11110 /
b1001 7
1&
#2600000
0&
#2610000
b1010 7
b11111 /
1&
#2620000
0&
#2630000
b100000 /
b1011 7
1&
#2640000
0&
#2650000
b1100 7
b100001 /
1&
#2660000
0&
#2670000
b100010 /
b1101 7
1&
#2680000
0&
#2690000
b1110 7
b100011 /
1&
#2700000
0&
#2710000
b100100 /
b1111 7
1&
#2720000
0&
#2730000
b10000 7
b100101 /
1&
#2740000
0&
#2750000
b100110 /
b10001 7
1&
#2760000
0&
#2770000
b10010 7
b100111 /
1&
#2780000
0&
#2790000
b101000 /
b10011 7
1&
#2800000
0&
#2810000
b10100 7
b101001 /
1&
#2820000
0&
#2830000
b101010 /
b10101 7
1&
#2840000
0&
#2850000
b10110 7
b101011 /
1&
#2860000
0&
#2870000
b101100 /
b10111 7
1&
#2880000
0&
#2890000
b11000 7
b101101 /
1&
#2900000
0&
#2910000
b101110 /
b11001 7
1&
#2920000
0&
#2930000
b11010 7
b101111 /
1&
#2940000
0&
#2950000
b110000 /
b11011 7
1&
#2960000
0&
#2970000
b11100 7
b110001 /
1&
#2980000
0&
#2990000
b10 .
b0 /
b11101 7
1&
#3000000
0&
#3010000
b11110 7
b1 /
1&
#3020000
0&
#3030000
b10 /
b11111 7
1&
#3040000
0&
#3050000
b100000 7
b11 /
1&
#3060000
0&
#3070000
b100 /
b100001 7
1&
#3080000
0&
#3090000
b100010 7
b101 /
1&
#3100000
0&
#3110000
b110 /
b100011 7
1&
#3120000
0&
#3130000
b100100 7
b111 /
1&
#3140000
0&
#3150000
b1000 /
b100101 7
1&
#3160000
0&
#3170000
b100110 7
b1001 /
1&
#3180000
0&
#3190000
b1010 /
b100111 7
1&
#3200000
0&
#3210000
b101000 7
b1011 /
1&
#3220000
0&
#3230000
b1100 /
b101001 7
1&
#3240000
0&
#3250000
b101010 7
b1101 /
1&
#3260000
0&
#3270000
b1110 /
b101011 7
1&
#3280000
0&
#3290000
b101100 7
b1111 /
1&
#3300000
0&
#3310000
b10000 /
b101101 7
1&
#3320000
0&
#3330000
b101110 7
b10001 /
1&
#3340000
0&
#3350000
b10010 /
b101111 7
1&
#3360000
0&
#3370000
b110000 7
b10011 /
1&
#3380000
0&
#3390000
b10100 /
b110001 7
1&
#3400000
0&
#3410000
b10 6
b0 7
b10101 /
1&
#3420000
0&
#3430000
b10110 /
b1 7
1!
1"
1&
#3440000
0&
#3450000
b10 7
13
b10111 /
1&
#3460000
0&
#3470000
b11000 /
12
b11 7
1&
#3480000
0&
#3490000
b100 7
b11001 /
1&
#3500000
0&
#3510000
b11010 /
b101 7
1&
#3520000
0&
#3530000
b110 7
b11011 /
1&
#3540000
0&
#3550000
b11100 /
b111 7
1&
#3560000
0&
#3570000
b1000 7
b11101 /
1&
#3580000
0&
#3590000
b11110 /
b1001 7
1&
#3600000
0&
#3610000
b1010 7
b11111 /
1&
#3620000
0&
#3630000
b100000 /
b1011 7
1&
#3640000
0&
#3650000
b1100 7
b100001 /
1&
#3660000
0&
#3670000
b100010 /
b1101 7
1&
#3680000
0&
#3690000
b1110 7
b100011 /
1&
#3700000
0&
#3710000
b100100 /
b1111 7
1&
#3720000
0&
#3730000
b10000 7
b100101 /
1&
#3740000
0&
#3750000
b100110 /
b10001 7
1&
#3760000
0&
#3770000
b10010 7
b100111 /
1&
#3780000
0&
#3790000
b101000 /
b10011 7
1&
#3800000
0&
#3810000
b10100 7
b101001 /
1&
#3820000
0&
#3830000
b101010 /
b10101 7
1&
#3840000
0&
#3850000
b10110 7
b101011 /
1&
#3860000
0&
#3870000
b101100 /
b10111 7
1&
#3880000
0&
#3890000
b11000 7
b101101 /
1&
#3900000
0&
#3910000
b101110 /
b11001 7
1&
#3920000
0&
#3930000
b11010 7
b101111 /
1&
#3940000
0&
#3950000
b110000 /
b11011 7
1&
#3960000
0&
#3970000
b11100 7
b110001 /
1&
#3980000
0&
#3990000
b11 .
b101 %
b101 ,
b101 -
b101 0
b0 /
b11101 7
1&
#4000000
0&
#4010000
b11110 7
b1 /
1&
#4020000
0&
#4030000
b10 /
b11111 7
1&
#4040000
0&
#4050000
b100000 7
b11 /
1&
#4060000
0&
#4070000
b100 /
b100001 7
1&
#4080000
0&
#4090000
b100010 7
b101 /
1&
#4100000
0&
#4110000
b110 /
b100011 7
1&
#4120000
0&
#4130000
b100100 7
b111 /
1&
#4140000
0&
#4150000
b1000 /
b100101 7
1&
#4160000
0&
#4170000
b100110 7
b1001 /
1&
#4180000
0&
#4190000
b1010 /
b100111 7
1&
#4200000
0&
#4210000
b101000 7
b1011 /
1&
#4220000
0&
#4230000
b1100 /
b101001 7
1&
#4240000
0&
#4250000
b101010 7
b1101 /
1&
#4260000
0&
#4270000
b1110 /
b101011 7
1&
#4280000
0&
#4290000
b101100 7
b1111 /
1&
#4300000
0&
#4310000
b10000 /
b101101 7
1&
#4320000
0&
#4330000
b101110 7
b10001 /
1&
#4340000
0&
#4350000
b10010 /
b101111 7
1&
#4360000
0&
#4370000
b110000 7
b10011 /
1&
#4380000
0&
#4390000
b10100 /
b110001 7
1&
#4400000
0&
#4410000
b11 6
b0 7
b10101 /
1&
#4420000
0&
#4430000
b10110 /
b1 7
0!
0"
1&
#4440000
0&
#4450000
b10 7
03
b10111 /
1&
#4460000
0&
#4470000
b11000 /
02
b11 7
1&
#4480000
0&
#4490000
b100 7
b11001 /
1&
#4500000
0&
#4510000
b11010 /
b101 7
1&
#4520000
0&
#4530000
b110 7
b11011 /
1&
#4540000
0&
#4550000
b11100 /
b111 7
1&
#4560000
0&
#4570000
b1000 7
b11101 /
1&
#4580000
0&
#4590000
b11110 /
b1001 7
1&
#4600000
0&
#4610000
b1010 7
b11111 /
1&
#4620000
0&
#4630000
b100000 /
b1011 7
1&
#4640000
0&
#4650000
b1100 7
b100001 /
1&
#4660000
0&
#4670000
b100010 /
b1101 7
1&
#4680000
0&
#4690000
b1110 7
b100011 /
1&
#4700000
0&
#4710000
b100100 /
b1111 7
1&
#4720000
0&
#4730000
b10000 7
b100101 /
1&
#4740000
0&
#4750000
b100110 /
b10001 7
1&
#4760000
0&
#4770000
b10010 7
b100111 /
1&
#4780000
0&
#4790000
b101000 /
b10011 7
1&
#4800000
0&
#4810000
b10100 7
b101001 /
1&
#4820000
0&
#4830000
b101010 /
b10101 7
1&
#4840000
0&
#4850000
b10110 7
b101011 /
1&
#4860000
0&
#4870000
b101100 /
b10111 7
1&
#4880000
0&
#4890000
b11000 7
b101101 /
1&
#4900000
0&
#4910000
b101110 /
b11001 7
1&
#4920000
0&
#4930000
b11010 7
b101111 /
1&
#4940000
0&
#4950000
b110000 /
b11011 7
1&
#4960000
0&
#4970000
b11100 7
b110001 /
1&
#4980000
0&
#4990000
b100 .
b0 /
b11101 7
1&
#5000000
0&
#5010000
b11110 7
b1 /
1&
#5020000
0&
#5030000
b10 /
b11111 7
1&
#5040000
0&
#5050000
b100000 7
b11 /
1&
#5060000
0&
#5070000
b100 /
b100001 7
1&
#5080000
0&
#5090000
b100010 7
b101 /
1&
#5100000
0&
#5110000
b110 /
b100011 7
1&
#5120000
0&
#5130000
b100100 7
b111 /
1&
#5140000
0&
#5150000
b1000 /
b100101 7
1&
#5160000
0&
#5170000
b100110 7
b1001 /
1&
#5180000
0&
#5190000
b1010 /
b100111 7
1&
#5200000
0&
#5210000
b101000 7
b1011 /
1&
#5220000
0&
#5230000
b1100 /
b101001 7
1&
#5240000
0&
#5250000
b101010 7
b1101 /
1&
#5260000
0&
#5270000
b1110 /
b101011 7
1&
#5280000
0&
#5290000
b101100 7
b1111 /
1&
#5300000
0&
#5310000
b10000 /
b101101 7
1&
#5320000
0&
#5330000
b101110 7
b10001 /
1&
#5340000
0&
#5350000
b10010 /
b101111 7
1&
#5360000
0&
#5370000
b110000 7
b10011 /
1&
#5380000
0&
#5390000
b10100 /
b110001 7
1&
#5400000
0&
#5410000
b100 6
b0 7
b10101 /
1&
#5420000
0&
#5430000
b10110 /
b1 7
1&
#5440000
0&
#5450000
b10 7
b10111 /
1&
#5460000
0&
#5470000
b11000 /
b11 7
1&
#5480000
0&
#5490000
b100 7
b11001 /
1&
#5500000
0&
#5510000
b11010 /
b101 7
1&
#5520000
0&
#5530000
b110 7
b11011 /
1&
#5540000
0&
#5550000
b11100 /
b111 7
1&
#5560000
0&
#5570000
b1000 7
b11101 /
1&
#5580000
0&
#5590000
b11110 /
b1001 7
1&
#5600000
0&
#5610000
b1010 7
b11111 /
1&
#5620000
0&
#5630000
b100000 /
b1011 7
1&
#5640000
0&
#5650000
b1100 7
b100001 /
1&
#5660000
0&
#5670000
b100010 /
b1101 7
1&
#5680000
0&
#5690000
b1110 7
b100011 /
1&
#5700000
0&
#5710000
b100100 /
b1111 7
1&
#5720000
0&
#5730000
b10000 7
b100101 /
1&
#5740000
0&
#5750000
b100110 /
b10001 7
1&
#5760000
0&
#5770000
b10010 7
b100111 /
1&
#5780000
0&
#5790000
b101000 /
b10011 7
1&
#5800000
0&
#5810000
b10100 7
b101001 /
1&
#5820000
0&
#5830000
b101010 /
b10101 7
1&
#5840000
0&
#5850000
b10110 7
b101011 /
1&
#5860000
0&
#5870000
b101100 /
b10111 7
1&
#5880000
0&
#5890000
b11000 7
b101101 /
1&
#5900000
0&
#5910000
b101110 /
b11001 7
1&
#5920000
0&
#5930000
b11010 7
b101111 /
1&
#5940000
0&
#5950000
b110000 /
b11011 7
1&
#5960000
0&
#5970000
b11100 7
b110001 /
1&
#5980000
0&
#5990000
b101 .
b0 /
b11101 7
1&
#6000000
0&
#6010000
b11110 7
b1 /
1&
#6020000
0&
#6030000
b10 /
b11111 7
1&
#6040000
0&
#6050000
b100000 7
b11 /
1&
#6060000
0&
#6070000
b100 /
b100001 7
1&
#6080000
0&
#6090000
b100010 7
b101 /
1&
#6100000
0&
#6110000
b110 /
b100011 7
1&
#6120000
0&
#6130000
b100100 7
b111 /
1&
#6140000
0&
#6150000
b1000 /
b100101 7
1&
#6160000
0&
#6170000
b100110 7
b1001 /
1&
#6180000
0&
#6190000
b1010 /
b100111 7
1&
#6200000
0&
#6210000
b101000 7
b1011 /
1&
#6220000
0&
#6230000
b1100 /
b101001 7
1&
#6240000
0&
#6250000
b101010 7
b1101 /
1&
#6260000
0&
#6270000
b1110 /
b101011 7
1&
#6280000
0&
#6290000
b101100 7
b1111 /
1&
#6300000
0&
#6310000
b10000 /
b101101 7
1&
#6320000
0&
#6330000
b101110 7
b10001 /
1&
#6340000
0&
#6350000
b10010 /
b101111 7
1&
#6360000
0&
#6370000
b110000 7
b10011 /
1&
#6380000
0&
#6390000
b10100 /
b110001 7
1&
#6400000
0&
#6410000
b101 6
b0 7
b10101 /
1&
#6420000
0&
#6430000
b10110 /
b1 7
1!
1"
1&
#6440000
0&
#6450000
b10 7
13
b10111 /
1&
#6460000
0&
#6470000
b11000 /
12
b11 7
1&
#6480000
0&
#6490000
b100 7
b11001 /
1&
#6500000
0&
#6510000
b11010 /
b101 7
1&
#6520000
0&
#6530000
b110 7
b11011 /
1&
#6540000
0&
#6550000
b11100 /
b111 7
1&
#6560000
0&
#6570000
b1000 7
b11101 /
1&
#6580000
0&
#6590000
b11110 /
b1001 7
1&
#6600000
0&
#6610000
b1010 7
b11111 /
1&
#6620000
0&
#6630000
b100000 /
b1011 7
1&
#6640000
0&
#6650000
b1100 7
b100001 /
1&
#6660000
0&
#6670000
b100010 /
b1101 7
1&
#6680000
0&
#6690000
b1110 7
b100011 /
1&
#6700000
0&
#6710000
b100100 /
b1111 7
1&
#6720000
0&
#6730000
b10000 7
b100101 /
1&
#6740000
0&
#6750000
b100110 /
b10001 7
1&
#6760000
0&
#6770000
b10010 7
b100111 /
1&
#6780000
0&
#6790000
b101000 /
b10011 7
1&
#6800000
0&
#6810000
b10100 7
b101001 /
1&
#6820000
0&
#6830000
b101010 /
b10101 7
1&
#6840000
0&
#6850000
b10110 7
b101011 /
1&
#6860000
0&
#6870000
b101100 /
b10111 7
1&
#6880000
0&
#6890000
b11000 7
b101101 /
1&
#6900000
0&
#6910000
b101110 /
b11001 7
1&
#6920000
0&
#6930000
b11010 7
b101111 /
1&
#6940000
0&
#6950000
b110000 /
b11011 7
1&
#6960000
0&
#6970000
b11100 7
b110001 /
1&
#6980000
0&
#6990000
b110 .
b100101 %
b100101 ,
b100101 -
b100101 0
b0 /
b11101 7
1&
#7000000
0&
#7010000
b11110 7
b1 /
1&
#7020000
0&
#7030000
b10 /
b11111 7
1&
#7040000
0&
#7050000
b100000 7
b11 /
1&
#7060000
0&
#7070000
b100 /
b100001 7
1&
#7080000
0&
#7090000
b100010 7
b101 /
1&
#7100000
0&
#7110000
b110 /
b100011 7
1&
#7120000
0&
